Wrench/__init__.py
Wrencher-0.1.9.dist-info/METADATA
Wrencher-0.1.9.dist-info/WHEEL
Wrencher-0.1.9.dist-info/top_level.txt
Wrencher-0.1.9.dist-info/RECORD
