Metadata-Version: 2.1
Name: Wrencher
Version: 0.1.9
Summary: Cool lib
Home-page: UNKNOWN
Author: Rostcraft
Author-email: UNKNOWN
License: MIT
Platform: UNKNOWN
